[
  {
    "group": "Emotion & Smileys",
    "group_image": "https://raw.githubusercontent.com/marquezmiguel/emojis/main/groups/emotion.png",
    "position": 1,
    "premium": 0,
    "premium_tier": 0,
    "articles": [
      {"emoji": "😀"},
      {"emoji": "😃"},
      {"emoji": "😄"},
      {"emoji": "😁"},
      {"emoji": "😆"},
      {"emoji": "😅"},
      {"emoji": "🤣"},
      {"emoji": "😂"},
      {"emoji": "🙂"},
      {"emoji": "🙃"},
      {"emoji": "🫠"},
      {"emoji": "😉"},
      {"emoji": "😊"},
      {"emoji": "😇"},
      {"emoji": "🥰"},
      {"emoji": "😍"},
      {"emoji": "🤩"},
      {"emoji": "😘"},
      {"emoji": "😗"},
      {"emoji": "☺️"},
      {"emoji": "😚"},
      {"emoji": "😙"},
      {"emoji": "🥲"},
      {"emoji": "😋"},
      {"emoji": "😛"},
      {"emoji": "😜"},
      {"emoji": "🤪"},
      {"emoji": "😝"},
      {"emoji": "🤑"},
      {"emoji": "🤗"},
      {"emoji": "🤭"},
      {"emoji": "🫢"},
      {"emoji": "🫣"},
      {"emoji": "🤫"},
      {"emoji": "🤔"},
      {"emoji": "🫡"},
      {"emoji": "🤐"},
      {"emoji": "🤨"},
      {"emoji": "😐️"},
      {"emoji": "😑"},
      {"emoji": "😶"},
      {"emoji": "🫥"},
      {"emoji": "😶‍🌫️"},
      {"emoji": "😏"},
      {"emoji": "😒"},
      {"emoji": "🙄"},
      {"emoji": "😬"},
      {"emoji": "😮‍💨"},
      {"emoji": "🫨"},
      {"emoji": "😌"},
      {"emoji": "😔"},
      {"emoji": "😪"},
      {"emoji": "🤤"},
      {"emoji": "😴"},
      {"emoji": "🫩"},
      {"emoji": "😷"},
      {"emoji": "🤕"},
      {"emoji": "🤢"},
      {"emoji": "🤮"},
      {"emoji": "🤧"},
      {"emoji": "🥵"},
      {"emoji": "🥶"},
      {"emoji": "🥴"},
      {"emoji": "😵‍💫"},
      {"emoji": "🤯"},
      {"emoji": "🥳"},
      {"emoji": "😎"},
      {"emoji": "🤓"},
      {"emoji": "🧐"},
      {"emoji": "😕"},
      {"emoji": "🫤"},
      {"emoji": "😟"},
      {"emoji": "🙁"},
      {"emoji": "☹️"},
      {"emoji": "😮"},
      {"emoji": "😯"},
      {"emoji": "😲"},
      {"emoji": "😳"},
      {"emoji": "🥺"},
      {"emoji": "🥹"},
      {"emoji": "😦"},
      {"emoji": "😧"},
      {"emoji": "😨"},
      {"emoji": "😰"},
      {"emoji": "😥"},
      {"emoji": "😢"},
      {"emoji": "😭"},
      {"emoji": "😱"},
      {"emoji": "😖"},
      {"emoji": "😣"},
      {"emoji": "😞"},
      {"emoji": "😓"},
      {"emoji": "😩"},
      {"emoji": "😫"},
      {"emoji": "🥱"},
      {"emoji": "😤"},
      {"emoji": "😡"},
      {"emoji": "😠"},
      {"emoji": "🤬"},
      {"emoji": "😈"},
      {"emoji": "👿"},
      {"emoji": "💀"},
      {"emoji": "☠️"},
      {"emoji": "💩"},
      {"emoji": "🤡"},
      {"emoji": "👻"},
      {"emoji": "👽️"},
      {"emoji": "💌"},
      {"emoji": "💘"},
      {"emoji": "💖"},
      {"emoji": "💗"},
      {"emoji": "💕"},
      {"emoji": "💔"},
      {"emoji": "❤️‍🔥"},
      {"emoji": "❤️‍🩹"},
      {"emoji": "❤️"},
      {"emoji": "🩷"},
      {"emoji": "🧡"},
      {"emoji": "💛"},
      {"emoji": "💚"},
      {"emoji": "💙"},
      {"emoji": "🩵"},
      {"emoji": "💜"},
      {"emoji": "🤎"},
      {"emoji": "🖤"},
      {"emoji": "🩶"},
      {"emoji": "🤍"},
      {"emoji": "💋"},
      {"emoji": "💯"},
      {"emoji": "💢"},
      {"emoji": "💥"},
      {"emoji": "💫"},
      {"emoji": "💦"},
      {"emoji": "💨"},
      {"emoji": "👁️‍🗨️"},
      {"emoji": "🗨️"},
      {"emoji": "💭"},
      {"emoji": "💤"}
    ]
  },
  {
    "group": "People & Body",
    "group_image": "https://raw.githubusercontent.com/marquezmiguel/emojis/main/groups/people.png",
    "position": 2,
    "premium": 0,
    "premium_tier": 0,
    "articles": [
      {"emoji": "👋"},
      {"emoji": "🤚"},
      {"emoji": "🖐️"},
      {"emoji": "✋️"},
      {"emoji": "🖖"},
      {"emoji": "🫱"},
      {"emoji": "🫲"},
      {"emoji": "🫳"},
      {"emoji": "🫴"},
      {"emoji": "🫷"},
      {"emoji": "🫸"},
      {"emoji": "👌"},
      {"emoji": "🤌"},
      {"emoji": "🤏"},
      {"emoji": "✌️"},
      {"emoji": "🤞"},
      {"emoji": "🫰"},
      {"emoji": "🤟"},
      {"emoji": "🤘"},
      {"emoji": "🤙"},
      {"emoji": "👈️"},
      {"emoji": "👉️"},
      {"emoji": "👆️"},
      {"emoji": "👇️"},
      {"emoji": "☝️"},
      {"emoji": "🫵"},
      {"emoji": "👍️"},
      {"emoji": "👎️"},
      {"emoji": "✊️"},
      {"emoji": "👊"},
      {"emoji": "🤛"},
      {"emoji": "🤜"},
      {"emoji": "👏"},
      {"emoji": "🙌"},
      {"emoji": "🫶"},
      {"emoji": "👐"},
      {"emoji": "🤲"},
      {"emoji": "🤝"},
      {"emoji": "🙏"},
      {"emoji": "💪"},
      {"emoji": "👀"},
      {"emoji": "👁️"},
      {"emoji": "🫦"}
    ]
  },
  {
    "group": "Animals & Nature",
    "group_image": "https://raw.githubusercontent.com/marquezmiguel/emojis/main/groups/nature.png",
    "position": 3,
    "premium": 0,
    "premium_tier": 0,
    "articles": [
      {"emoji": "🐵"},
      {"emoji": "🐶"},
      {"emoji": "🐺"},
      {"emoji": "🦊"},
      {"emoji": "🐱"},
      {"emoji": "🐯"},
      {"emoji": "🐴"},
      {"emoji": "🐮"},
      {"emoji": "🐭"},
      {"emoji": "🐰"},
      {"emoji": "🦇"},
      {"emoji": "🐻"},
      {"emoji": "🐼"},
      {"emoji": "🐔"},
      {"emoji": "🐤"},
      {"emoji": "🐥"},
      {"emoji": "🪶"},
      {"emoji": "🪽"},
      {"emoji": "🐸"},
      {"emoji": "🐍"},
      {"emoji": "🐉"},
      {"emoji": "🦋"},
      {"emoji": "🕷️"},
      {"emoji": "🌸"},
      {"emoji": "💮"},
      {"emoji": "🏵️"},
      {"emoji": "🌹"},
      {"emoji": "🌻"},
      {"emoji": "🌲"},
      {"emoji": "🌳"},
      {"emoji": "🌵"},
      {"emoji": "🌿"},
      {"emoji": "☘️"},
      {"emoji": "🍀"},
      {"emoji": "🍂"}
    ]
  },
  {
    "group": "Food & Drink",
    "group_image": "https://raw.githubusercontent.com/marquezmiguel/emojis/main/groups/food.png",
    "position": 4,
    "premium": 0,
    "premium_tier": 0,
    "articles": [
      {"emoji": "🍌"},
      {"emoji": "🍎"},
      {"emoji": "🍏"},
      {"emoji": "🍒"},
      {"emoji": "🥖"},
      {"emoji": "🥚"},
      {"emoji": "🎂"},
      {"emoji": "🍺"},
      {"emoji": "🍻"}
    ]
  },
  {
    "group": "Travel & Places",
    "group_image": "https://raw.githubusercontent.com/marquezmiguel/emojis/main/groups/travel.png",
    "position": 5,
    "premium": 0,
    "premium_tier": 0,
    "articles": [
      {"emoji": "🚔️"},
      {"emoji": "🛻"},
      {"emoji": "🛵"},
      {"emoji": "🚨"},
      {"emoji": "🛑"},
      {"emoji": "🕘️"},
      {"emoji": "🌙"},
      {"emoji": "🌜️"},
      {"emoji": "☀️"},
      {"emoji": "🌝"},
      {"emoji": "🌞"},
      {"emoji": "⭐️"},
      {"emoji": "🌟"},
      {"emoji": "🌠"},
      {"emoji": "☁️"},
      {"emoji": "⛅️"},
      {"emoji": "⛈️"},
      {"emoji": "🌤️"},
      {"emoji": "🌥️"},
      {"emoji": "🌦️"},
      {"emoji": "🌨️"},
      {"emoji": "🌪️"},
      {"emoji": "🌈"},
      {"emoji": "⚡️"},
      {"emoji": "❄️"},
      {"emoji": "⛄️"},
      {"emoji": "🔥"},
      {"emoji": "💧"},
      {"emoji": "🌊"}
    ]
  },
  {
    "group": "Activities",
    "group_image": "https://raw.githubusercontent.com/marquezmiguel/emojis/main/groups/activities.png",
    "position": 6,
    "premium": 0,
    "premium_tier": 0,
    "articles": [
      {"emoji": "🎃"},
      {"emoji": "🎇"},
      {"emoji": "✨️"},
      {"emoji": "🎉"},
      {"emoji": "🎊"},
      {"emoji": "🧧"},
      {"emoji": "🎀"},
      {"emoji": "🎁"},
      {"emoji": "🎟️"},
      {"emoji": "🎫"},
      {"emoji": "🎖️"},
      {"emoji": "🏆️"},
      {"emoji": "🏅"},
      {"emoji": "🥇"},
      {"emoji": "🥈"},
      {"emoji": "🥉"},
      {"emoji": "🔮"},
      {"emoji": "🎲"},
      {"emoji": "🧸"}
    ]
  },
  {
    "group": "Objects",
    "group_image": "https://raw.githubusercontent.com/marquezmiguel/emojis/main/groups/objects.png",
    "position": 7,
    "premium": 0,
    "premium_tier": 0,
    "articles": [
      {"emoji": "👑"},
      {"emoji": "🔔"},
      {"emoji": "💡"},
      {"emoji": "🔖"},
      {"emoji": "✉️"},
      {"emoji": "📩"},
      {"emoji": "🔒️"},
      {"emoji": "⛏️"},
      {"emoji": "🗡️"},
      {"emoji": "⚔️"},
      {"emoji": "🏹"},
      {"emoji": "🛡️"},
      {"emoji": "⚖️"},
      {"emoji": "🩹"},
      {"emoji": "🚬"},
      {"emoji": "🪦"}
    ]
  },
  {
    "group": "Symbols",
    "group_image": "https://raw.githubusercontent.com/marquezmiguel/emojis/main/groups/symbols.png",
    "position": 8,
    "premium": 0,
    "premium_tier": 0,
    "articles": [
      {"emoji": "⚠️"},
      {"emoji": "⛔️"},
      {"emoji": "🚫"},
      {"emoji": "⬆️"},
      {"emoji": "➡️"},
      {"emoji": "⬇️"},
      {"emoji": "⬅️"},
      {"emoji": "📶"},
      {"emoji": "➕️"},
      {"emoji": "➖️"},
      {"emoji": "‼️"},
      {"emoji": "⁉️"},
      {"emoji": "❓️"},
      {"emoji": "❔️"},
      {"emoji": "❕️"},
      {"emoji": "❗️"},
      {"emoji": "✅️"},
      {"emoji": "✔️"},
      {"emoji": "❌️"},
      {"emoji": "🆘"}
    ]
  },
  {
    "group": "Flags",
    "group_image": "https://raw.githubusercontent.com/marquezmiguel/emojis/main/groups/flags.png",
    "position": 9,
    "premium": 0,
    "premium_tier": 0,
    "articles": [
      {"emoji": "🏁"},
      {"emoji": "🚩"},
      {"emoji": "🎌"},
      {"emoji": "🏴"},
      {"emoji": "🏳️"},
      {"emoji": "🏳️‍🌈"},
      {"emoji": "🏳️‍⚧️"},
      {"emoji": "🏴‍☠️"},
      {"emoji": "🇦🇨"},
      {"emoji": "🇦🇩"},
      {"emoji": "🇦🇪"},
      {"emoji": "🇦🇫"},
      {"emoji": "🇦🇬"},
      {"emoji": "🇦🇮"},
      {"emoji": "🇦🇱"},
      {"emoji": "🇦🇲"},
      {"emoji": "🇦🇴"},
      {"emoji": "🇦🇶"},
      {"emoji": "🇦🇷"},
      {"emoji": "🇦🇸"},
      {"emoji": "🇦🇹"},
      {"emoji": "🇦🇺"},
      {"emoji": "🇦🇼"},
      {"emoji": "🇦🇽"},
      {"emoji": "🇦🇿"},
      {"emoji": "🇧🇦"},
      {"emoji": "🇧🇧"},
      {"emoji": "🇧🇩"},
      {"emoji": "🇧🇪"},
      {"emoji": "🇧🇫"},
      {"emoji": "🇧🇬"},
      {"emoji": "🇧🇭"},
      {"emoji": "🇧🇮"},
      {"emoji": "🇧🇯"},
      {"emoji": "🇧🇱"},
      {"emoji": "🇧🇲"},
      {"emoji": "🇧🇳"},
      {"emoji": "🇧🇴"},
      {"emoji": "🇧🇶"},
      {"emoji": "🇧🇷"},
      {"emoji": "🇧🇸"},
      {"emoji": "🇧🇹"},
      {"emoji": "🇧🇻"},
      {"emoji": "🇧🇼"},
      {"emoji": "🇧🇾"},
      {"emoji": "🇧🇿"},
      {"emoji": "🇨🇦"},
      {"emoji": "🇨🇨"},
      {"emoji": "🇨🇩"},
      {"emoji": "🇨🇫"},
      {"emoji": "🇨🇬"},
      {"emoji": "🇨🇭"},
      {"emoji": "🇨🇮"},
      {"emoji": "🇨🇰"},
      {"emoji": "🇨🇱"},
      {"emoji": "🇨🇲"},
      {"emoji": "🇨🇳"},
      {"emoji": "🇨🇴"},
      {"emoji": "🇨🇵"},
      {"emoji": "🇨🇶"},
      {"emoji": "🇨🇷"},
      {"emoji": "🇨🇺"},
      {"emoji": "🇨🇻"},
      {"emoji": "🇨🇼"},
      {"emoji": "🇨🇽"},
      {"emoji": "🇨🇾"},
      {"emoji": "🇨🇿"},
      {"emoji": "🇩🇪"},
      {"emoji": "🇩🇬"},
      {"emoji": "🇩🇯"},
      {"emoji": "🇩🇰"},
      {"emoji": "🇩🇲"},
      {"emoji": "🇩🇴"},
      {"emoji": "🇩🇿"},
      {"emoji": "🇪🇦"},
      {"emoji": "🇪🇨"},
      {"emoji": "🇪🇪"},
      {"emoji": "🇪🇬"},
      {"emoji": "🇪🇭"},
      {"emoji": "🇪🇷"},
      {"emoji": "🇪🇸"},
      {"emoji": "🇪🇹"},
      {"emoji": "🇪🇺"},
      {"emoji": "🇫🇮"},
      {"emoji": "🇫🇯"},
      {"emoji": "🇫🇰"},
      {"emoji": "🇫🇲"},
      {"emoji": "🇫🇴"},
      {"emoji": "🇫🇷"},
      {"emoji": "🇬🇦"},
      {"emoji": "🇬🇧"},
      {"emoji": "🇬🇩"},
      {"emoji": "🇬🇪"},
      {"emoji": "🇬🇫"},
      {"emoji": "🇬🇬"},
      {"emoji": "🇬🇭"},
      {"emoji": "🇬🇮"},
      {"emoji": "🇬🇱"},
      {"emoji": "🇬🇲"},
      {"emoji": "🇬🇳"},
      {"emoji": "🇬🇵"},
      {"emoji": "🇬🇶"},
      {"emoji": "🇬🇷"},
      {"emoji": "🇬🇸"},
      {"emoji": "🇬🇹"},
      {"emoji": "🇬🇺"},
      {"emoji": "🇬🇼"},
      {"emoji": "🇬🇾"},
      {"emoji": "🇭🇰"},
      {"emoji": "🇭🇲"},
      {"emoji": "🇭🇳"},
      {"emoji": "🇭🇷"},
      {"emoji": "🇭🇹"},
      {"emoji": "🇭🇺"},
      {"emoji": "🇮🇨"},
      {"emoji": "🇮🇩"},
      {"emoji": "🇮🇪"},
      {"emoji": "🇮🇱"},
      {"emoji": "🇮🇲"},
      {"emoji": "🇮🇳"},
      {"emoji": "🇮🇴"},
      {"emoji": "🇮🇶"},
      {"emoji": "🇮🇷"},
      {"emoji": "🇮🇸"},
      {"emoji": "🇮🇹"},
      {"emoji": "🇯🇪"},
      {"emoji": "🇯🇲"},
      {"emoji": "🇯🇴"},
      {"emoji": "🇯🇵"},
      {"emoji": "🇰🇪"},
      {"emoji": "🇰🇬"},
      {"emoji": "🇰🇭"},
      {"emoji": "🇰🇮"},
      {"emoji": "🇰🇲"},
      {"emoji": "🇰🇳"},
      {"emoji": "🇰🇵"},
      {"emoji": "🇰🇷"},
      {"emoji": "🇰🇼"},
      {"emoji": "🇰🇾"},
      {"emoji": "🇰🇿"},
      {"emoji": "🇱🇦"},
      {"emoji": "🇱🇧"},
      {"emoji": "🇱🇨"},
      {"emoji": "🇱🇮"},
      {"emoji": "🇱🇰"},
      {"emoji": "🇱🇷"},
      {"emoji": "🇱🇸"},
      {"emoji": "🇱🇹"},
      {"emoji": "🇱🇺"},
      {"emoji": "🇱🇻"},
      {"emoji": "🇱🇾"},
      {"emoji": "🇲🇦"},
      {"emoji": "🇲🇨"},
      {"emoji": "🇲🇩"},
      {"emoji": "🇲🇪"},
      {"emoji": "🇲🇫"},
      {"emoji": "🇲🇬"},
      {"emoji": "🇲🇭"},
      {"emoji": "🇲🇰"},
      {"emoji": "🇲🇱"},
      {"emoji": "🇲🇲"},
      {"emoji": "🇲🇳"},
      {"emoji": "🇲🇴"},
      {"emoji": "🇲🇵"},
      {"emoji": "🇲🇶"},
      {"emoji": "🇲🇷"},
      {"emoji": "🇲🇸"},
      {"emoji": "🇲🇹"},
      {"emoji": "🇲🇺"},
      {"emoji": "🇲🇻"},
      {"emoji": "🇲🇼"},
      {"emoji": "🇲🇽"},
      {"emoji": "🇲🇾"},
      {"emoji": "🇲🇿"},
      {"emoji": "🇳🇦"},
      {"emoji": "🇳🇨"},
      {"emoji": "🇳🇪"},
      {"emoji": "🇳🇫"},
      {"emoji": "🇳🇬"},
      {"emoji": "🇳🇮"},
      {"emoji": "🇳🇱"},
      {"emoji": "🇳🇴"},
      {"emoji": "🇳🇵"},
      {"emoji": "🇳🇷"},
      {"emoji": "🇳🇺"},
      {"emoji": "🇳🇿"},
      {"emoji": "🇴🇲"},
      {"emoji": "🇵🇦"},
      {"emoji": "🇵🇪"},
      {"emoji": "🇵🇫"},
      {"emoji": "🇵🇬"},
      {"emoji": "🇵🇭"},
      {"emoji": "🇵🇰"},
      {"emoji": "🇵🇱"},
      {"emoji": "🇵🇲"},
      {"emoji": "🇵🇳"},
      {"emoji": "🇵🇷"},
      {"emoji": "🇵🇸"},
      {"emoji": "🇵🇹"},
      {"emoji": "🇵🇼"},
      {"emoji": "🇵🇾"},
      {"emoji": "🇶🇦"},
      {"emoji": "🇷🇪"},
      {"emoji": "🇷🇴"},
      {"emoji": "🇷🇸"},
      {"emoji": "🇷🇺"},
      {"emoji": "🇷🇼"},
      {"emoji": "🇸🇦"},
      {"emoji": "🇸🇧"},
      {"emoji": "🇸🇨"},
      {"emoji": "🇸🇩"},
      {"emoji": "🇸🇪"},
      {"emoji": "🇸🇬"},
      {"emoji": "🇸🇭"},
      {"emoji": "🇸🇮"},
      {"emoji": "🇸🇯"},
      {"emoji": "🇸🇰"},
      {"emoji": "🇸🇱"},
      {"emoji": "🇸🇲"},
      {"emoji": "🇸🇳"},
      {"emoji": "🇸🇴"},
      {"emoji": "🇸🇷"},
      {"emoji": "🇸🇸"},
      {"emoji": "🇸🇹"},
      {"emoji": "🇸🇻"},
      {"emoji": "🇸🇽"},
      {"emoji": "🇸🇾"},
      {"emoji": "🇸🇿"},
      {"emoji": "🇹🇦"},
      {"emoji": "🇹🇨"},
      {"emoji": "🇹🇩"},
      {"emoji": "🇹🇫"},
      {"emoji": "🇹🇬"},
      {"emoji": "🇹🇭"},
      {"emoji": "🇹🇯"},
      {"emoji": "🇹🇰"},
      {"emoji": "🇹🇱"},
      {"emoji": "🇹🇲"},
      {"emoji": "🇹🇳"},
      {"emoji": "🇹🇴"},
      {"emoji": "🇹🇷"},
      {"emoji": "🇹🇹"},
      {"emoji": "🇹🇻"},
      {"emoji": "🇹🇼"},
      {"emoji": "🇹🇿"},
      {"emoji": "🇺🇦"},
      {"emoji": "🇺🇬"},
      {"emoji": "🇺🇲"},
      {"emoji": "🇺🇳"},
      {"emoji": "🇺🇸"},
      {"emoji": "🇺🇾"},
      {"emoji": "🇺🇿"},
      {"emoji": "🇻🇦"},
      {"emoji": "🇻🇨"},
      {"emoji": "🇻🇪"},
      {"emoji": "🇻🇬"},
      {"emoji": "🇻🇮"},
      {"emoji": "🇻🇳"},
      {"emoji": "🇻🇺"},
      {"emoji": "🇼🇫"},
      {"emoji": "🇼🇸"},
      {"emoji": "🇽🇰"},
      {"emoji": "🇾🇪"},
      {"emoji": "🇾🇹"},
      {"emoji": "🇿🇦"},
      {"emoji": "🇿🇲"},
      {"emoji": "🇿🇼"},
      {"emoji": "🏴󠁧󠁢󠁥󠁮󠁧󠁿"},
      {"emoji": "🏴󠁧󠁢󠁳󠁣󠁴󠁿"},
      {"emoji": "🏴󠁧󠁢󠁷󠁬󠁳󠁿"}
    ]
  }
]
